pyopendoc/__init__.py
pyopendoc/exceptions.py
pyopendoc/namespaces.py
pyopendoc/opendocument.py
pyopendoc/singlefile.py
pyopendoc/spreadsheet.py
pyopendoc/writer.py
pyopendoc/elements/__init__.py
pyopendoc/elements/element.py
pyopendoc/elements/table.py
pyopendoc/elements/text.py
pyopendoc-0.4.2.dist-info/DESCRIPTION.rst
pyopendoc-0.4.2.dist-info/METADATA
pyopendoc-0.4.2.dist-info/RECORD
pyopendoc-0.4.2.dist-info/WHEEL
pyopendoc-0.4.2.dist-info/metadata.json
pyopendoc-0.4.2.dist-info/top_level.txt
test/__init__.py
test/test_spreadsheet.py
