Metadata-Version: 2.0
Name: pyopendoc
Version: 0.4.2
Summary: Open Office Document manipulation module
Home-page: https://github.com/mbwk/pyopendoc
Author: Red Ape Solutions Sdn Bhd
Author-email: karl@redapesolutions.com
License: UNKNOWN
Download-URL: https://github.com/mbwk/pyopendoc/tarball/0.4.2
Platform: UNKNOWN
Classifier: Development Status :: 3 - Alpha
